avro/__init__.py
avro/main.py
avro/core/__init__.py
avro/core/config.py
avro/core/count.py
avro/core/processor.py
avro/core/validate.py
avro/resources/__init__.py
avro/resources/dictionary.py
avro_py-2025.10.10.dist-info/METADATA
avro_py-2025.10.10.dist-info/WHEEL
avro_py-2025.10.10.dist-info/licenses/LICENSE
avro_py-2025.10.10.dist-info/RECORD
