Metadata-Version: 2.4
Name: avro-py
Version: 2025.10.10
Summary: A modern Pythonic implementation of Avro Phonetic.
Project-URL: Homepage, https://pypi.org/project/avro-py
Project-URL: Documentation, https://hitblast.github.io/avro.py
Project-URL: Repository, https://github.com/hitblast/avro.py
Author-email: Anindya Shiddhartha <hitblastlive@gmail.com>
License: MIT License
License-File: LICENSE
Keywords: avro,avro phonetic,bangla,bengali,bengali phonetics,phonetics,python,transliteration
Classifier: Intended Audience :: Developers
Classifier: License :: OSI Approved :: MIT License
Classifier: Operating System :: OS Independent
Classifier: Programming Language :: Python :: 3.10
Classifier: Programming Language :: Python :: 3.11
Classifier: Programming Language :: Python :: 3.12
Classifier: Programming Language :: Python :: 3.13
Classifier: Programming Language :: Python :: 3.14
Classifier: Topic :: Software Development :: Libraries :: Python Modules
Requires-Python: >=3.10
